pyverto/__about__.py
pyverto/__init__.py
pyverto/__main__.py
pyverto/header.py
pyverto/regexp.py
pyverto/utils.py
pyverto/vc.py
pyverto-0.2.1.dist-info/METADATA
pyverto-0.2.1.dist-info/WHEEL
pyverto-0.2.1.dist-info/entry_points.txt
pyverto-0.2.1.dist-info/licenses/LICENSE
pyverto-0.2.1.dist-info/RECORD
