Metadata-Version: 2.4
Name: pyverto
Version: 0.2.1
Summary: A python package version management tool.
Project-URL: Documentation, https://github.com/phdenzel/pyverto#readme
Project-URL: Issues, https://github.com/phdenzel/pyverto/issues
Project-URL: Source, https://github.com/phdenzel/pyverto
Author-email: phdenzel <phdenzel@gmail.com>
License-Expression: MIT
License-File: LICENSE
Keywords: package version management,version bump
Classifier: Development Status :: 4 - Beta
Classifier: Programming Language :: Python
Classifier: Programming Language :: Python :: 3.10
Classifier: Programming Language :: Python :: 3.11
Classifier: Programming Language :: Python :: 3.12
Classifier: Programming Language :: Python :: 3.13
Classifier: Programming Language :: Python :: Implementation :: CPython
Classifier: Programming Language :: Python :: Implementation :: PyPy
Requires-Python: >=3.10
Requires-Dist: gitpython>=3.1.44
Requires-Dist: tomli; python_version < '3.11'
